wikistream/__init__.py
wikistream/__main__.py
wikistream/aiosseclient/LICENSE
wikistream/aiosseclient/MANIFEST.in
wikistream/aiosseclient/README.md
wikistream/aiosseclient/aiosseclient.py
wikistream/aiosseclient/requirements.txt
wikistream/aiosseclient/setup.py
wikistream/client.py
wikistream-0.2.2.dist-info/LICENSE.md
wikistream-0.2.2.dist-info/WHEEL
wikistream-0.2.2.dist-info/METADATA
wikistream-0.2.2.dist-info/RECORD
